py_func_lib/__init__.py
py_func_lib/function/__init__.py
py_func_lib/function/curry.py
py_func_lib/function/curry.test.py
py_func_lib-0.0.1.dist-info/LICENSE
py_func_lib-0.0.1.dist-info/METADATA
py_func_lib-0.0.1.dist-info/WHEEL
py_func_lib-0.0.1.dist-info/top_level.txt
py_func_lib-0.0.1.dist-info/RECORD
