Metadata-Version: 2.1
Name: py-func-lib
Version: 0.0.1
Summary: Functional Library for Python.
Home-page: https://github.com/jcuffney/py-func-lib
Author: Joe Cuffney
Author-email: josephcuffney@gmail.com
License: UNKNOWN
Platform: UNKNOWN
Classifier: Programming Language :: Python :: 3
Classifier: License :: OSI Approved :: MIT License
Classifier: Operating System :: OS Independent
